Metadata-Version: 1.1
Name: django-emailtemplates
Version: 1.1.2
Summary: A simple Django app to create emails based on database or filesystem templates.
Home-page: https://github.com/deployed/django-emailtemplates
Author: Wiktor Kolodziej
Author-email: UNKNOWN
License: MIT License
Platform: UNKNOWN
Classifier: Environment :: Web Environment
Classifier: Framework :: Django
Classifier: Intended Audience :: Developers
Classifier: License :: OSI Approved :: MIT License
Classifier: Operating System :: OS Independent
Classifier: Programming Language :: Python
Classifier: Programming Language :: Python :: 2.7
Classifier: Topic :: Internet :: WWW/HTTP
Classifier: Topic :: Internet :: WWW/HTTP :: Dynamic Content
